{
  "id": "e-commerce-microservices-env",
  "name": "E-commerce Microservices Environment",
  "values": [
    {
      "key": "baseUrl",
      "value": "http://localhost:4000",
      "description": "API Gateway base URL",
      "enabled": true,
      "type": "default"
    },
    {
      "key": "adminEmail",
      "value": "admin@example.com",
      "description": "Admin account email",
      "enabled": true,
      "type": "default"
    },
    {
      "key": "adminPassword",
      "value": "admin123",
      "description": "Admin account password",
      "enabled": true,
      "type": "default"
    },
    {
      "key": "customerEmail",
      "value": "customer@gmail.com", 
      "description": "Customer account email",
      "enabled": true,
      "type": "default"
    },
    {
      "key": "customerPassword",
      "value": "customer123",
      "description": "Customer account password",
      "enabled": true,
      "type": "default"
    },
    {
      "key": "adminToken",
      "value": "",
      "description": "Admin JWT token (auto-populated after login)",
      "enabled": true,
      "type": "default"
    },
    {
      "key": "userToken",
      "value": "",
      "description": "User JWT token (auto-populated after login)",
      "enabled": true,
      "type": "default"
    },
    {
      "key": "productId",
      "value": "",
      "description": "Product ID for testing (auto-populated)",
      "enabled": true,
      "type": "default"
    },
    {
      "key": "orderId",
      "value": "",
      "description": "Order ID for testing (auto-populated)",
      "enabled": true,
      "type": "default"
    },
    {
      "key": "paymentId",
      "value": "",
      "description": "Payment ID for testing (auto-populated)",
      "enabled": true,
      "type": "default"
    }
  ],
  "_postman_variable_scope": "environment"
}
